audiomath/BackEnd.py
audiomath/Base.py
audiomath/COPYING
audiomath/Dependencies.py
audiomath/DependencyManagement.py
audiomath/FakePyGame.py
audiomath/Functional.py
audiomath/GenericInterface.py
audiomath/Graphics.py
audiomath/IO.py
audiomath/MASTER_META
audiomath/Meta.py
audiomath/PortAudioInterface.py
audiomath/PsychToolboxInterface.py
audiomath/PsychoPyInterface.py
audiomath/Queueing.py
audiomath/Signal.py
audiomath/StretchAndShift.py
audiomath/SystemVolume.py
audiomath/__init__.py
audiomath/__main__.py
audiomath/pycaw_fork.py
audiomath/_wrap_avbin/README+LICENSE.md
audiomath/_wrap_avbin/__init__.py
audiomath/_wrap_avbin/libavbin-Darwin-64bit.dylib
audiomath/_wrap_avbin/libavbin-Darwin-arm64.dylib
audiomath/_wrap_avbin/libavbin-Linux-64bit.so
audiomath/_wrap_avbin/libavbin-Windows-32bit.dll
audiomath/_wrap_avbin/libavbin-Windows-64bit.dll
audiomath/_wrap_portaudio/README+LICENSE.md
audiomath/_wrap_portaudio/__init__.py
audiomath/_wrap_portaudio/_dll_wrapper.py
audiomath/_wrap_portaudio/libportaudio-Darwin-64bit.dylib
audiomath/_wrap_portaudio/libportaudio-Darwin-arm64.dylib
audiomath/_wrap_portaudio/libportaudio-Linux-64bit.so
audiomath/_wrap_portaudio/libportaudio-Windows-32bit.dll
audiomath/_wrap_portaudio/libportaudio-Windows-64bit.dll
audiomath/accel/__init__.py
audiomath/accel/libaudiochunk-Darwin-64bit.dylib
audiomath/accel/libaudiochunk-Darwin-arm64.dylib
audiomath/accel/libaudiochunk-Linux-64bit.so
audiomath/accel/libaudiochunk-Windows-32bit.dll
audiomath/accel/libaudiochunk-Windows-64bit.dll
audiomath/example_media/test12345678.wav
audiomath-1.21.4.dist-info/licenses/COPYING
audiomath-1.21.4.dist-info/METADATA
audiomath-1.21.4.dist-info/WHEEL
audiomath-1.21.4.dist-info/top_level.txt
audiomath-1.21.4.dist-info/RECORD
