Metadata-Version: 2.4
Name: audiomath
Version: 1.21.4
Summary: A package for recording, reading, manipulating, playing and writing sound files
Home-page: https://audiomath.readthedocs.io
Author: Jeremy Hill
Author-email: jezhill@gmail.com
License: GPL v3+
Requires-Python: >=2.7, !=3.0.*, !=3.1.*, !=3.2.*, <4
License-File: COPYING
Requires-Dist: numpy
Requires-Dist: psutil; platform_system == "Windows"
Requires-Dist: comtypes; platform_system == "Windows"
Provides-Extra: plotting
Requires-Dist: matplotlib; extra == "plotting"
Provides-Extra: stretching
Requires-Dist: librosa; extra == "stretching"
Provides-Extra: audioread
Requires-Dist: audioread; extra == "audioread"
Dynamic: author
Dynamic: author-email
Dynamic: description
Dynamic: description-content-type
Dynamic: home-page
Dynamic: license
Dynamic: license-file
Dynamic: provides-extra
Dynamic: requires-dist
Dynamic: requires-python
Dynamic: summary
